sasl/saslwrapper.cpython-37m-x86_64-linux-gnu.so
sasl/__init__.py
sasl/saslwrapper.pyx
sasl/saslwrapper.h
sasl/saslwrapper.cpp
sasl.libs/libsasl2-e96a0dbf.so.2.0.22
sasl.libs/libcrypt-36ce9caf.so.1.1.0
sasl-0.3.dist-info/RECORD
sasl-0.3.dist-info/METADATA
sasl-0.3.dist-info/top_level.txt
sasl-0.3.dist-info/LICENSE.txt
sasl-0.3.dist-info/WHEEL
