Metadata-Version: 2.1
Name: sasl
Version: 0.3
Summary: Cyrus-SASL bindings for Python
Home-page: http://github.com/cloudera/python-sasl
Maintainer: Todd Lipcon
Maintainer-email: todd@cloudera.com
License: Apache License, Version 2.0
Platform: UNKNOWN
Classifier: Programming Language :: Python :: 2
Classifier: Programming Language :: Python :: 3
License-File: LICENSE.txt
Requires-Dist: six
